ch3_2_setup.py
upload_dnatools.egg-info/PKG-INFO
upload_dnatools.egg-info/SOURCES.txt
upload_dnatools.egg-info/dependency_links.txt
upload_dnatools.egg-info/top_level.txt